csvs_update_sqlite/__init__.py
csvs_update_sqlite/cli.py
csvs_update_sqlite/utils.py
csvs_update_sqlite-1.3.11.dist-info/LICENSE
csvs_update_sqlite-1.3.11.dist-info/METADATA
csvs_update_sqlite-1.3.11.dist-info/WHEEL
csvs_update_sqlite-1.3.11.dist-info/entry_points.txt
csvs_update_sqlite-1.3.11.dist-info/top_level.txt
csvs_update_sqlite-1.3.11.dist-info/RECORD
