Metadata-Version: 2.1
Name: csvs-update-sqlite
Version: 1.3.11
Summary: Convert CSV files into a SQLite database
Home-page: https://github.com/dkaoster/csvs-update-sqlite
Author: Daniel Kao
License: Apache License, Version 2.0
Platform: UNKNOWN
Classifier: Intended Audience :: Developers
Classifier: Intended Audience :: Science/Research
Classifier: Intended Audience :: End Users/Desktop
Classifier: Topic :: Database
Classifier: License :: OSI Approved :: Apache Software License
Classifier: Programming Language :: Python :: 3.6
Classifier: Programming Language :: Python :: 3.7
Classifier: Programming Language :: Python :: 3.8
Classifier: Programming Language :: Python :: 3.9
License-File: LICENSE
Requires-Dist: click ~=7.0
Requires-Dist: dateparser >=1.0
Requires-Dist: pandas >=1.0
Requires-Dist: py-lru-cache ~=0.1.4
Requires-Dist: six
Provides-Extra: test
Requires-Dist: pytest ; extra == 'test'
Requires-Dist: cogapp ; extra == 'test'
